MANIFEST.in
README.markdown
setup.py
huSoftM.egg-info/PKG-INFO
huSoftM.egg-info/SOURCES.txt
huSoftM.egg-info/dependency_links.txt
huSoftM.egg-info/not-zip-safe
huSoftM.egg-info/requires.txt
huSoftM.egg-info/top_level.txt
husoftm/__init__.py
husoftm/artikel.py
husoftm/auftraege.py
husoftm/bestaende.py
husoftm/bestellungen.py
husoftm/connection.py
husoftm/connection2.py
husoftm/fields.py
husoftm/kunden.py
husoftm/lagerschnittstelle.py
husoftm/lieferanten.py
husoftm/lieferscheine.py
husoftm/misc.py
husoftm/mock_as400.py
husoftm/preise_ek.py
husoftm/rechnungen.py
husoftm/sachbearbeiter.py
husoftm/softmtables.py
husoftm/stapelschnittstelle.py
husoftm/stapelschnittstelle_const.py
husoftm/tools.py
husoftm/versandart.py