Metadata-Version: 1.0
Name: huSoftM
Version: 0.65p2
Summary: communication with the SoftM Suite on an AS/400
Home-page: http://github.com/hudora/huSoftM#readme
Author: Maximillian Dornseif
Author-email: md@hudora.de
License: UNKNOWN
Platform: UNKNOWN
Classifier: License :: OSI Approved :: BSD License
Classifier: Intended Audience :: Developers
Classifier: Programming Language :: Python
